{"addr": "18Z5yiY8ewQ9paVsxn8zhvRQRza3UmuRjg", "total_sent": 2182893544, "total_received": 2182893544, "received_from": [{"addr": "1Gi1cSfw9xs6mvRVTNzfL6T2LfRQFVcPhj", "value": 16808000.0, "time": 1597896219, "gm_time": "2020-08-20 04:03:39", "local_time": "2020-08-20 12:03:39"}, {"addr": "bc1q22xl0kn406fcj3wasdnpc5jcu7azq4wafu0qeey2cffn24gspkws00n09a", "value": 728216.1818434029, "time": 1597205090, "gm_time": "2020-08-12 04:04:50", "local_time": "2020-08-12 12:04:50"}, {"addr": "bc1qq60kldvynedwwz5thgte5du0tvuuaqlmjk9e2hkzhdyrn37me78qrmrhh0", "value": 12265388.818156598, "time": 1597205090, "gm_time": "2020-08-12 04:04:50", "local_time": "2020-08-12 12:04:50"}, {"addr": "bc1qp87f9j3dtv8e89erhc48m6wv7lkwe6g4s6z0trcsr0l943lesmxqf9rdht", "value": 8251731.0, "time": 1596949399, "gm_time": "2020-08-09 05:03:19", "local_time": "2020-08-09 13:03:19"}, {"addr": "1MRi6ohJac3cCZqw5Dc2WeDv2mi8ZzDbF2", "value": 398754.77192982455, "time": 1596916508, "gm_time": "2020-08-08 19:55:08", "local_time": "2020-08-09 03:55:08"}, {"addr": "1KWnxqYVdk3N4ggmxFo4M2wcRMNfHDEwGD", "value": 6380076.350877193, "time": 1596916508, "gm_time": "2020-08-08 19:55:08", "local_time": "2020-08-09 03:55:08"}, {"addr": "1Bb5CJnNekJwvdA9EKW4ztuwHj9UVXozru", "value": 3190038.1754385964, "time": 1596916508, "gm_time": "2020-08-08 19:55:08", "local_time": "2020-08-09 03:55:08"}, {"addr": "1CLk3Gwqu99QioCpzmheYBGwwqK6UwPPNk", "value": 12760152.701754386, "time": 1596916508, "gm_time": "2020-08-08 19:55:08", "local_time": "2020-08-09 03:55:08"}, {"addr": "bc1qwcx3zvkwswya8wc9z4fulgkpykjhzxv098ucd82dmzx0djhzh3ss7e22f3", "value": 4240376.0, "time": 1596862024, "gm_time": "2020-08-08 04:47:04", "local_time": "2020-08-08 12:47:04"}, {"addr": "bc1qv2ueq5z2aqtfqeervgdscxemxw72p3c4x7hsn2v58z8sjfnsahpskyf6qs", "value": 8400257.0, "time": 1596861560, "gm_time": "2020-08-08 04:39:20", "local_time": "2020-08-08 12:39:20"}, {"addr": "1Kv9XR11XVVivs1zdaVtWzTsxaLkah8Tmp", "value": 11343580.397381205, "time": 1596833247, "gm_time": "2020-08-07 20:47:27", "local_time": "2020-08-08 04:47:27"}, {"addr": "1QJHCLe1LyDY6ZpfytjDbckxRf13WT8MgB", "value": 107908.60261879543, "time": 1596833247, "gm_time": "2020-08-07 20:47:27", "local_time": "2020-08-08 04:47:27"}, {"addr": "16Qckf66z76UoR3xo1Xf1mvoMNNEa2KvjZ", "value": 5718711.02069355, "time": 1596687088, "gm_time": "2020-08-06 04:11:28", "local_time": "2020-08-06 12:11:28"}, {"addr": "12WSBpeKqMY4y51JmC9QuPvThuEsUL1KFx", "value": 2699600.97930645, "time": 1596687088, "gm_time": "2020-08-06 04:11:28", "local_time": "2020-08-06 12:11:28"}, {"addr": "17vEnXH14x5yZynFiZZNQLpZwVBem6DqJV", "value": 8326020.108240482, "time": 1596108812, "gm_time": "2020-07-30 11:33:32", "local_time": "2020-07-30 19:33:32"}, {"addr": "13HhVxqPjEFqJMWBgSKqofH3w17rQPSf34", "value": 4740852.7904215045, "time": 1596108812, "gm_time": "2020-07-30 11:33:32", "local_time": "2020-07-30 19:33:32"}, {"addr": "16Yt7nwVo3AaPGd71gYbvg9HaKF8AhuYMk", "value": 6970660.4007124035, "time": 1596108812, "gm_time": "2020-07-30 11:33:32", "local_time": "2020-07-30 19:33:32"}, {"addr": "1HyupdjvDvsz8A9ei2qf9WWXgkitTq4Dfo", "value": 875801.7006256086, "time": 1596108812, "gm_time": "2020-07-30 11:33:32", "local_time": "2020-07-30 19:33:32"}, {"addr": "bc1q40r4ldxncsqpedrcq9h2ttvkttefzcuhnjju7d7zrf283wazfcssng5wyh", "value": 3590285.0, "time": 1595999410, "gm_time": "2020-07-29 05:10:10", "local_time": "2020-07-29 13:10:10"}, {"addr": "16FtcjZSW9ABuoiVeVtcQKw6psC6BopTCz", "value": 153907.0629461044, "time": 1595994151, "gm_time": "2020-07-29 03:42:31", "local_time": "2020-07-29 11:42:31"}, {"addr": "1LqMdXRfFGt1oFTqmtpxTpmjsosGxM218p", "value": 44983.937053895614, "time": 1595994151, "gm_time": "2020-07-29 03:42:31", "local_time": "2020-07-29 11:42:31"}, {"addr": "15FNBWghDmeJ5cqjqiDFMHMc627AxQacrZ", "value": 1653840.0, "time": 1595965798, "gm_time": "2020-07-28 19:49:58", "local_time": "2020-07-29 03:49:58"}, {"addr": "1EAfKaWPqz2B1VP5Gvm8etvhGH8AmTaaVk", "value": 470309.71816250146, "time": 1595961373, "gm_time": "2020-07-28 18:36:13", "local_time": "2020-07-29 02:36:13"}, {"addr": "1Q5bzMVuc2fdQn9cAJjh72DEyfndPkLHgt", "value": 441590.28183749854, "time": 1595961373, "gm_time": "2020-07-28 18:36:13", "local_time": "2020-07-29 02:36:13"}, {"addr": "1B7CxbE5iZMrt1ZxBoDMrNb9BWNi3szdfM", "value": 228650.0, "time": 1595926973, "gm_time": "2020-07-28 09:02:53", "local_time": "2020-07-28 17:02:53"}, {"addr": "1Eprcj43kx5x7Nzb8CcLFKwUStj8s4rbL7", "value": 9832.0, "time": 1595847754, "gm_time": "2020-07-27 11:02:34", "local_time": "2020-07-27 19:02:34"}, {"addr": "1QCcNFyCM1SbNBEZSzuTsc3my71YaWGXGx", "value": 953934.0, "time": 1595803072, "gm_time": "2020-07-26 22:37:52", "local_time": "2020-07-27 06:37:52"}, {"addr": "173yHSjZBRKWa8jesFatNEx96iefpo2vyY", "value": 907560.0, "time": 1595790883, "gm_time": "2020-07-26 19:14:43", "local_time": "2020-07-27 03:14:43"}, {"addr": "3PUv9tQMSDCEPSMsYSopA5wDW86pwRFbNF", "value": 2572622.0, "time": 1595718739, "gm_time": "2020-07-25 23:12:19", "local_time": "2020-07-26 07:12:19"}, {"addr": "1HQ71eryYYp8GZWWiTbZBkqK3hQg3KZv6N", "value": 10220475.769797292, "time": 1595707893, "gm_time": "2020-07-25 20:11:33", "local_time": "2020-07-26 04:11:33"}, {"addr": "1G5z9RAJEXWmyABuFXqwJLTUmUYaQpJn2B", "value": 7531.2302027072365, "time": 1595707893, "gm_time": "2020-07-25 20:11:33", "local_time": "2020-07-26 04:11:33"}, {"addr": "1NmAKiyxYUTveTkJZwUeXv7jR9gXhi6Eu1", "value": 10542720.0, "time": 1595704560, "gm_time": "2020-07-25 19:16:00", "local_time": "2020-07-26 03:16:00"}, {"addr": "1zoFVu9HYVRoP2Re3HQytq6eDae7hBASF", "value": 537826.1428733232, "time": 1595626865, "gm_time": "2020-07-24 21:41:05", "local_time": "2020-07-25 05:41:05"}, {"addr": "1DNFx2zePaH6gZKLCHt1CyVYsF43mEqPK", "value": 416357.6914737171, "time": 1595626865, "gm_time": "2020-07-24 21:41:05", "local_time": "2020-07-25 05:41:05"}, {"addr": "1NkzVa4Zz8tNJkKmbJSYuJgMiLFrC1t7gA", "value": 354941.1656529597, "time": 1595626865, "gm_time": "2020-07-24 21:41:05", "local_time": "2020-07-25 05:41:05"}, {"addr": "1e8WCCzjmRv4ptLF7FQbvzUN2bZL5BiA9", "value": 9988403.0, "time": 1595607775, "gm_time": "2020-07-24 16:22:55", "local_time": "2020-07-25 00:22:55"}, {"addr": "1HnL3R2P1uXFNpq2xcBpQvyVtPCZ2U7dKk", "value": 15434717.513029218, "time": 1595607775, "gm_time": "2020-07-24 16:22:55", "local_time": "2020-07-25 00:22:55"}, {"addr": "1G7QKzXUPB2tkv8Uo8mvzMYuXPZGedHYcc", "value": 12919175.486970784, "time": 1595607775, "gm_time": "2020-07-24 16:22:55", "local_time": "2020-07-25 00:22:55"}, {"addr": "1CE4dS16vYYzXXnukg4VyokM1YLV1tcXxL", "value": 20466895.0, "time": 1595607386, "gm_time": "2020-07-24 16:16:26", "local_time": "2020-07-25 00:16:26"}, {"addr": "16KN74J8SpAMdmguhvCc5ddStB2zpEzz7j", "value": 5153469.2051615, "time": 1595602458, "gm_time": "2020-07-24 14:54:18", "local_time": "2020-07-24 22:54:18"}, {"addr": "15wcMJbFrDLffF2Kya91uSkGRBtSM9WDCa", "value": 10836.24386362941, "time": 1595602458, "gm_time": "2020-07-24 14:54:18", "local_time": "2020-07-24 22:54:18"}, {"addr": "17B39odvt2dgvSPjnPyKifRSniBfbGCcx3", "value": 20467562.550974872, "time": 1595602458, "gm_time": "2020-07-24 14:54:18", "local_time": "2020-07-24 22:54:18"}, {"addr": "1GaUozYQigtmPmHVCNyh87QTkCfb6ZQ2eZ", "value": 5160703.944220773, "time": 1595594668, "gm_time": "2020-07-24 12:44:28", "local_time": "2020-07-24 20:44:28"}, {"addr": "14FpkzXdK1ak2W3hrRPYYRBXQgqQw13bH2", "value": 5337296.055779227, "time": 1595594668, "gm_time": "2020-07-24 12:44:28", "local_time": "2020-07-24 20:44:28"}, {"addr": "1CE4dS16vYYzXXnukg4VyokM1YLV1tcXxL", "value": 10291986.0, "time": 1595594630, "gm_time": "2020-07-24 12:43:50", "local_time": "2020-07-24 20:43:50"}, {"addr": "1P3zWtDCGBpgt6juWcHQNveqrExdhMTuAq", "value": 584874.3200629471, "time": 1595585643, "gm_time": "2020-07-24 10:14:03", "local_time": "2020-07-24 18:14:03"}, {"addr": "19UBVJwoqmDkAumx9Wh7Cs9w75Ca1sLGVY", "value": 7962886.542553859, "time": 1595585643, "gm_time": "2020-07-24 10:14:03", "local_time": "2020-07-24 18:14:03"}, {"addr": "1NoooaZKUen1ZLNLe4WAtahjSzFx8hKnKm", "value": 1862678.3545394249, "time": 1595585643, "gm_time": "2020-07-24 10:14:03", "local_time": "2020-07-24 18:14:03"}, {"addr": "13vUypy4QZQSirkske7kD8hgSPyvYMTSSL", "value": 3851661.78284377, "time": 1595585643, "gm_time": "2020-07-24 10:14:03", "local_time": "2020-07-24 18:14:03"}, {"addr": "1FfCWHF2VQNzXae2iHHeCWp5X6B6Sk6GEX", "value": 18406468.045997914, "time": 1595581100, "gm_time": "2020-07-24 08:58:20", "local_time": "2020-07-24 16:58:20"}, {"addr": "19kyPpAvngA6GXArEuimQ4UHdrW7HPNfbe", "value": 1543850.9540020851, "time": 1595581100, "gm_time": "2020-07-24 08:58:20", "local_time": "2020-07-24 16:58:20"}, {"addr": "1vsxTLKUFmwWSYFSiHc4H79jDmK85m57s", "value": 3322812.0, "time": 1595537564, "gm_time": "2020-07-23 20:52:44", "local_time": "2020-07-24 04:52:44"}, {"addr": "bc1q2mf8q00wl0h3sun8ycpnn3aeppm7ps83yz9tpc", "value": 4993842.0, "time": 1595526964, "gm_time": "2020-07-23 17:56:04", "local_time": "2020-07-24 01:56:04"}, {"addr": "1EBizWT4mZjgTySMiGpBZ6ivGjMYyG9zTn", "value": 8721949.49773616, "time": 1595521980, "gm_time": "2020-07-23 16:33:00", "local_time": "2020-07-24 00:33:00"}, {"addr": "1PNzgzFBChArQnrW3UmQH9aiwG2r5XkcZW", "value": 996717.2536472956, "time": 1595521980, "gm_time": "2020-07-23 16:33:00", "local_time": "2020-07-24 00:33:00"}, {"addr": "1HyC8Z9JRSyqQYq9t6ZhL1FYv5e8WCcvXh", "value": 1938210.9994969247, "time": 1595521980, "gm_time": "2020-07-23 16:33:00", "local_time": "2020-07-24 00:33:00"}, {"addr": "1Fe1Bv8yPpMt1oGm2oD4KQ9L2YP7hCgVy2", "value": 2907316.499245387, "time": 1595521980, "gm_time": "2020-07-23 16:33:00", "local_time": "2020-07-24 00:33:00"}, {"addr": "1Ny5w4LyVx4eyq4M4ssN645Q4AVJvczzNV", "value": 484552.7498742312, "time": 1595521980, "gm_time": "2020-07-23 16:33:00", "local_time": "2020-07-24 00:33:00"}, {"addr": "1DLjieNWqnr8AYEg5RtqG5275RPPNo8Z2j", "value": 20703480.0, "time": 1595516782, "gm_time": "2020-07-23 15:06:22", "local_time": "2020-07-23 23:06:22"}, {"addr": "193DoJze2tT4SUYvPBRKv3qGL6YNKkE4Hi", "value": 12779533.0, "time": 1595443548, "gm_time": "2020-07-22 18:45:48", "local_time": "2020-07-23 02:45:48"}, {"addr": "1HJyPxsuo9aEgcPewgGjoby539qNpTAZjD", "value": 3179533.0, "time": 1595443548, "gm_time": "2020-07-22 18:45:48", "local_time": "2020-07-23 02:45:48"}, {"addr": "1DGQPXQGgYU7taMSccAgssijtP6c3NZdfD", "value": 179533.0, "time": 1595443548, "gm_time": "2020-07-22 18:45:48", "local_time": "2020-07-23 02:45:48"}, {"addr": "1MtjJorLSFx1CBik1KFLLyFn6JfgPL6hBX", "value": 379533.0, "time": 1595443548, "gm_time": "2020-07-22 18:45:48", "local_time": "2020-07-23 02:45:48"}, {"addr": "1P1tXoUemj37a6mCYC7QLbEwf9v7o4wRcY", "value": 320878.0, "time": 1595439268, "gm_time": "2020-07-22 17:34:28", "local_time": "2020-07-23 01:34:28"}, {"addr": "1HqR9URn69ki2QyJ7AoenoYbV8GCARy8yd", "value": 534890.9888973504, "time": 1595418499, "gm_time": "2020-07-22 11:48:19", "local_time": "2020-07-22 19:48:19"}, {"addr": "1N669C7ovY3URZUeRZpHNppjctVdfpbdqL", "value": 535309.0111026496, "time": 1595418499, "gm_time": "2020-07-22 11:48:19", "local_time": "2020-07-22 19:48:19"}, {"addr": "12jzvXvSsHqjeGEYaPL87kfP7WCsWGKiQV", "value": 447048.0, "time": 1595378008, "gm_time": "2020-07-22 00:33:28", "local_time": "2020-07-22 08:33:28"}, {"addr": "1HGY9jewtvaHJPBWGCVCETt8axkhtsa3oE", "value": 380685.0, "time": 1595375015, "gm_time": "2020-07-21 23:43:35", "local_time": "2020-07-22 07:43:35"}, {"addr": "19yfTcEHh92f5UYDUTTmJ38mhQVD6jy6hw", "value": 3180685.0, "time": 1595375015, "gm_time": "2020-07-21 23:43:35", "local_time": "2020-07-22 07:43:35"}, {"addr": "1JqjWE4pATnEBHudC1qKDVkczrty9tUd1q", "value": 1580685.0, "time": 1595375015, "gm_time": "2020-07-21 23:43:35", "local_time": "2020-07-22 07:43:35"}, {"addr": "13yoWJpouCCU4Xw37G15rFryD7HFYkgWNz", "value": 400881.8096121439, "time": 1595356253, "gm_time": "2020-07-21 18:30:53", "local_time": "2020-07-22 02:30:53"}, {"addr": "1HYxnUwwSoUTrndAuZVjUFoJQdCqQt8hnm", "value": 95684.23503411068, "time": 1595356253, "gm_time": "2020-07-21 18:30:53", "local_time": "2020-07-22 02:30:53"}, {"addr": "1GvJW8rdyK8ziX5H1RXi6rMfkiPsKsAsKZ", "value": 36915.955353745376, "time": 1595356253, "gm_time": "2020-07-21 18:30:53", "local_time": "2020-07-22 02:30:53"}, {"addr": "17x4TMGfH8dCt9HVBxjmh7KKYyYhzrLijD", "value": 5680158.0, "time": 1595353540, "gm_time": "2020-07-21 17:45:40", "local_time": "2020-07-22 01:45:40"}, {"addr": "19ofxUSvh4pmjNfrMoHTAZrariRQxyXmGn", "value": 25458129.866753314, "time": 1595346790, "gm_time": "2020-07-21 15:53:10", "local_time": "2020-07-21 23:53:10"}, {"addr": "1LDsFy5wr58oVNqDeBsA5eiYnyLxA4KziK", "value": 9574685.133246688, "time": 1595346790, "gm_time": "2020-07-21 15:53:10", "local_time": "2020-07-21 23:53:10"}, {"addr": "1Cb6HVqg8gEPGt1JRboePwENtFjTYHDGwd", "value": 10898000.0, "time": 1595287365, "gm_time": "2020-07-20 23:22:45", "local_time": "2020-07-21 07:22:45"}, {"addr": "3PUv9tQMSDCEPSMsYSopA5wDW86pwRFbNF", "value": 330281.0, "time": 1595280219, "gm_time": "2020-07-20 21:23:39", "local_time": "2020-07-21 05:23:39"}, {"addr": "13vTCh54E4CPoek8zPxRdCnHCEKNwnQyXn", "value": 817629.0, "time": 1595279730, "gm_time": "2020-07-20 21:15:30", "local_time": "2020-07-21 05:15:30"}, {"addr": "3LUufJHmCxTyYJ5EqUMZmDi4xnxsfh5W5N", "value": 1786851.0, "time": 1595012086, "gm_time": "2020-07-17 18:54:46", "local_time": "2020-07-18 02:54:46"}, {"addr": "bc1qsnhedmt2f2g49rht0tcvc0m0rlle7npcnuvvk0ns8cfmkpqmu7xqfffxvh", "value": 213642.0, "time": 1595011130, "gm_time": "2020-07-17 18:38:50", "local_time": "2020-07-18 02:38:50"}, {"addr": "1L8hsGZMfzk229k9GDY1mxBTDdZ5GWN21e", "value": 26318400.0, "time": 1595005976, "gm_time": "2020-07-17 17:12:56", "local_time": "2020-07-18 01:12:56"}, {"addr": "19kKjintH77AWMxUUvGbij6RDDysVhe1Hq", "value": 7569513.15637375, "time": 1594999664, "gm_time": "2020-07-17 15:27:44", "local_time": "2020-07-17 23:27:44"}, {"addr": "1BJu8YLKysBidd125s1op9meLsoui4jucN", "value": 7715686.8436262505, "time": 1594999664, "gm_time": "2020-07-17 15:27:44", "local_time": "2020-07-17 23:27:44"}, {"addr": "1Ja8vJfNFJnEjN29oEEJTY4zjMaRi626Nv", "value": 21495384.776352353, "time": 1594947691, "gm_time": "2020-07-17 01:01:31", "local_time": "2020-07-17 09:01:31"}, {"addr": "12X1fUiCKpxbJcyxbzQV3NJi5dpu8Tk35S", "value": 6507866.223647647, "time": 1594947691, "gm_time": "2020-07-17 01:01:31", "local_time": "2020-07-17 09:01:31"}, {"addr": "bc1qptjp2gjqmag4ptk857ehtp8tdgjeyes7fs5kwjzpxj6d3jk4eh5s5at5sg", "value": 321475.0, "time": 1594933778, "gm_time": "2020-07-16 21:09:38", "local_time": "2020-07-17 05:09:38"}, {"addr": "15ESJ3aEHgH2skhRSBmLoLUWHRMwauX1kD", "value": 145751.8128781415, "time": 1594932413, "gm_time": "2020-07-16 20:46:53", "local_time": "2020-07-17 04:46:53"}, {"addr": "1FKHEfVDNGjvXfCEpdzP4V4VUfAmY6UuuF", "value": 28634.812128351434, "time": 1594932413, "gm_time": "2020-07-16 20:46:53", "local_time": "2020-07-17 04:46:53"}, {"addr": "1F6usGvaA1WfW4HbiASxhqosXngGscdbug", "value": 40556.37499350705, "time": 1594932413, "gm_time": "2020-07-16 20:46:53", "local_time": "2020-07-17 04:46:53"}, {"addr": "167dYrBMEkAnGHQ8fPhDSta2yd8Xj9MNqz", "value": 218763.0, "time": 1594926628, "gm_time": "2020-07-16 19:10:28", "local_time": "2020-07-17 03:10:28"}, {"addr": "17RnDUbf87MXJz8k4ZxB2ctizrsJ5STVUK", "value": 822991.0, "time": 1594914025, "gm_time": "2020-07-16 15:40:25", "local_time": "2020-07-16 23:40:25"}, {"addr": "1L6uirddYDQ3zHWPFyCU73nn94FPuTqtBQ", "value": 545643.0, "time": 1594882989, "gm_time": "2020-07-16 07:03:09", "local_time": "2020-07-16 15:03:09"}, {"addr": "bc1qqle5dj3m2s6sdcn3ay45j9ylkwlakmhqll8dveavhe0lqx5jq6jqjnmahu", "value": 11313897.242475582, "time": 1594859664, "gm_time": "2020-07-16 00:34:24", "local_time": "2020-07-16 08:34:24"}, {"addr": "bc1qdx99g9rz36xe4zk7dtksfgat5t85js208aukgtg5z4exvmkwtg7qv90rkx", "value": 9686102.757524418, "time": 1594859664, "gm_time": "2020-07-16 00:34:24", "local_time": "2020-07-16 08:34:24"}, {"addr": "1HMigCBSFfJKZTiRrPaY46UeiqLeUygfPy", "value": 541846.0, "time": 1594849937, "gm_time": "2020-07-15 21:52:17", "local_time": "2020-07-16 05:52:17"}, {"addr": "17s8VDzDmC32rtSU1fTaBoA2XFf9bRD33h", "value": 6895459.0, "time": 1594843579, "gm_time": "2020-07-15 20:06:19", "local_time": "2020-07-16 04:06:19"}], "sent_to": [{"addr": "15wNCNLWbNa1kxi5GLvQHzTURSjiQ7H8T5", "value": 67304.0, "time": 1599731103, "gm_time": "2020-09-10 09:45:03", "local_time": "2020-09-10 17:45:03"}, {"addr": "1PBsrzmmu9CYPNLTrYq85obiEzeEJnXd44", "value": 17527.253512990304, "time": 1598184512, "gm_time": "2020-08-23 12:08:32", "local_time": "2020-08-23 20:08:32"}, {"addr": "1BPULhbGfrojrknyD7aZYMtRVUu38Cn75j", "value": 25221736.74648701, "time": 1598184512, "gm_time": "2020-08-23 12:08:32", "local_time": "2020-08-23 20:08:32"}, {"addr": "12N535g4ZUnpC9YFoQZKH1x7rygRHL6ssr", "value": 9242131.835331995, "time": 1597215681, "gm_time": "2020-08-12 07:01:21", "local_time": "2020-08-12 15:01:21"}, {"addr": "1BPULhbGfrojrknyD7aZYMtRVUu38Cn75j", "value": 26480495.16466801, "time": 1597215681, "gm_time": "2020-08-12 07:01:21", "local_time": "2020-08-12 15:01:21"}, {"addr": "1BPULhbGfrojrknyD7aZYMtRVUu38Cn75j", "value": 40001560.0, "time": 1596917774, "gm_time": "2020-08-08 20:16:14", "local_time": "2020-08-09 04:16:14"}, {"addr": "1M8ZmmzG3ahMZKB1fHnVXtoWCbWFDs3hQf", "value": 2619107.8610173515, "time": 1596792352, "gm_time": "2020-08-07 09:25:52", "local_time": "2020-08-07 17:25:52"}, {"addr": "1J57zoCiJdzGNihXQayhNrPpNFXmvfUMVH", "value": 18294227.13898265, "time": 1596792352, "gm_time": "2020-08-07 09:25:52", "local_time": "2020-08-07 17:25:52"}, {"addr": "19e4xbeMpriohydNRCSQe8qiGoRsZa3tMo", "value": 44669.56662707826, "time": 1595937194, "gm_time": "2020-07-28 11:53:14", "local_time": "2020-07-28 19:53:14"}, {"addr": "1BPULhbGfrojrknyD7aZYMtRVUu38Cn75j", "value": 25561738.433372922, "time": 1595937194, "gm_time": "2020-07-28 11:53:14", "local_time": "2020-07-28 19:53:14"}, {"addr": "19nAq7jM1ofW76GPCN2oD2w9A2A2So8ymN", "value": 918691.0130701171, "time": 1595610183, "gm_time": "2020-07-24 17:03:03", "local_time": "2020-07-25 01:03:03"}, {"addr": "1BPULhbGfrojrknyD7aZYMtRVUu38Cn75j", "value": 94020367.98692988, "time": 1595610183, "gm_time": "2020-07-24 17:03:03", "local_time": "2020-07-25 01:03:03"}, {"addr": "1MPyBFwHmGgWTR7KwAqADzTmfqwiaVY7TV", "value": 1443131.5525464376, "time": 1595594630, "gm_time": "2020-07-24 12:43:50", "local_time": "2020-07-24 20:43:50"}, {"addr": "1BPULhbGfrojrknyD7aZYMtRVUu38Cn75j", "value": 43061274.447453566, "time": 1595594630, "gm_time": "2020-07-24 12:43:50", "local_time": "2020-07-24 20:43:50"}, {"addr": "16jsKgxj8WUqCnc57J5a1ybvZMk2VZiRbo", "value": 84464.19585227483, "time": 1595578894, "gm_time": "2020-07-24 08:21:34", "local_time": "2020-07-24 16:21:34"}, {"addr": "1BPULhbGfrojrknyD7aZYMtRVUu38Cn75j", "value": 51107717.80414772, "time": 1595578894, "gm_time": "2020-07-24 08:21:34", "local_time": "2020-07-24 16:21:34"}, {"addr": "19NhZhT4zDMS3vwCqAnP6aX2ue5nH1jD7G", "value": 405130.89065397746, "time": 1595456101, "gm_time": "2020-07-22 22:15:01", "local_time": "2020-07-23 06:15:01"}, {"addr": "1BPULhbGfrojrknyD7aZYMtRVUu38Cn75j", "value": 21385505.10934602, "time": 1595456101, "gm_time": "2020-07-22 22:15:01", "local_time": "2020-07-23 06:15:01"}, {"addr": "1Bgv2G6LVHdDqui9bYGC67SDBfRZ94DkmL", "value": 80875.4222616077, "time": 1595353540, "gm_time": "2020-07-21 17:45:40", "local_time": "2020-07-22 01:45:40"}, {"addr": "1BPULhbGfrojrknyD7aZYMtRVUu38Cn75j", "value": 53693476.57773839, "time": 1595353540, "gm_time": "2020-07-21 17:45:40", "local_time": "2020-07-22 01:45:40"}, {"addr": "16Fw1vfcDqtYnzTtQkNwH6nsQe9zTsfmmQ", "value": 35218.12088489295, "time": 1595284770, "gm_time": "2020-07-20 22:39:30", "local_time": "2020-07-21 06:39:30"}, {"addr": "1BPULhbGfrojrknyD7aZYMtRVUu38Cn75j", "value": 53383742.879115105, "time": 1595284770, "gm_time": "2020-07-20 22:39:30", "local_time": "2020-07-21 06:39:30"}, {"addr": "1MdS6NU1LAA7KDQiv5tYcC8TV6WBVkd1wk", "value": 4378385.576390381, "time": 1595046215, "gm_time": "2020-07-18 04:23:35", "local_time": "2020-07-18 12:23:35"}, {"addr": "18HrZB4RDAcya7FUVDakSWQJBDm1hgDuNf", "value": 46938175.42360962, "time": 1595046215, "gm_time": "2020-07-18 04:23:35", "local_time": "2020-07-18 12:23:35"}, {"addr": "1Dxia86337f1RKy1dqyacg2KRZk6gjTYev", "value": 4433862.533090185, "time": 1595005976, "gm_time": "2020-07-17 17:12:56", "local_time": "2020-07-18 01:12:56"}, {"addr": "18HrZB4RDAcya7FUVDakSWQJBDm1hgDuNf", "value": 21884537.466909815, "time": 1595005976, "gm_time": "2020-07-17 17:12:56", "local_time": "2020-07-18 01:12:56"}, {"addr": "12zDWF6ZxU56r11XJD7PgB76xkugHoyUMW", "value": 4359061.425050125, "time": 1594908034, "gm_time": "2020-07-16 14:00:34", "local_time": "2020-07-16 22:00:34"}, {"addr": "18HrZB4RDAcya7FUVDakSWQJBDm1hgDuNf", "value": 16640938.574949875, "time": 1594908034, "gm_time": "2020-07-16 14:00:34", "local_time": "2020-07-16 22:00:34"}]}