{"addr": "1HvSimpW5XXzTv1GboSmuAPeBBPaZwHwxs", "total_sent": 400000, "total_received": 400000, "received_from": [{"addr": "12GVyB2vuRpyEVWt4a5YYemwf2idjiSGgq", "value": 381694.7931647799, "time": 1595379408, "gm_time": "2020-07-22 00:56:48", "local_time": "2020-07-22 08:56:48"}, {"addr": "15ej1bv2UZjY3ndaU7zaFyKT33gp57bhEd", "value": 18305.206835220084, "time": 1595379408, "gm_time": "2020-07-22 00:56:48", "local_time": "2020-07-22 08:56:48"}], "sent_to": [{"addr": "15iPiL9WnCmLVDqM5u595CDHeHCpqGsMJC", "value": 400000.0, "time": 1595395206, "gm_time": "2020-07-22 05:20:06", "local_time": "2020-07-22 13:20:06"}]}